scriptbox/__init__.py
scriptbox/screencapture.py
scriptbox-0.1.0a0.data/data/man/man1/screencapture.1
scriptbox-0.1.0a0.data/data/man/man1/scriptbox.1
scriptbox-0.1.0a0.dist-info/LICENSE.txt
scriptbox-0.1.0a0.dist-info/METADATA
scriptbox-0.1.0a0.dist-info/WHEEL
scriptbox-0.1.0a0.dist-info/entry_points.txt
scriptbox-0.1.0a0.dist-info/top_level.txt
scriptbox-0.1.0a0.dist-info/RECORD
