Metadata-Version: 2.1
Name: scriptbox
Version: 0.1.0a0
Summary: Small everyday utilities for variety of tasks
Author: Niklas Larsson
License: UNKNOWN
Project-URL: Bug Reports, https://github.com/nikkelarsson/scriptbox/issues
Project-URL: Source, https://github.com/nikkelarsson/scriptbox
Keywords: utilities
Platform: UNKNOWN
Classifier: Development Status :: 3 - Alpha
Classifier: Intended Audience :: End Users/Desktop
Classifier: License :: OSI Approved :: MIT License
Classifier: Programming Language :: Python :: 3
Requires-Python: >=3.10
License-File: LICENSE.txt
